MultiOCRPlot/__init__.py
MultiOCRPlot/compute_performance.py
MultiOCRPlot/get_performance_plot.py
MultiOCRPlot/get_time_plot.py
MultiOCRPlot-2.1.dist-info/METADATA
MultiOCRPlot-2.1.dist-info/WHEEL
MultiOCRPlot-2.1.dist-info/top_level.txt
MultiOCRPlot-2.1.dist-info/RECORD
